.DS_Store
gptchem/__init__.py
gptchem/cli.py
gptchem/data.py
gptchem/evaluator.py
gptchem/extractor.py
gptchem/formatter.py
gptchem/generator.py
gptchem/gpt_classifier.py
gptchem/gpt_regressor.py
gptchem/kevin.mplstyle
gptchem/plotsettings.py
gptchem/plotutils.py
gptchem/py.typed
gptchem/querier.py
gptchem/representation.py
gptchem/settings.py
gptchem/tuner.py
gptchem/types.py
gptchem/utils.py
gptchem/version.py
gptchem/baselines/__init__.py
gptchem/baselines/balasz.py
gptchem/baselines/bandgap.py
gptchem/baselines/cv.py
gptchem/baselines/esol.py
gptchem/baselines/freesolv.py
gptchem/baselines/henry.py
gptchem/baselines/lipophilicity.py
gptchem/baselines/opv.py
gptchem/baselines/photoswitch.py
gptchem/baselines/polymer.py
gptchem/baselines/randomforest.py
gptchem/baselines/rxn.py
gptchem/baselines/solubility.py
gptchem/baselines/water_stability.py
gptchem/fingerprints/__init__.py
gptchem/fingerprints/mol_fingerprints.py
gptchem/fingerprints/polymer.py
gptchem/models/__init__.py
gptchem/models/base.py
gptchem/models/gpr.py
gptchem/models/xgboost.py
gptchem-0.0.5.dist-info/LICENSE
gptchem-0.0.5.dist-info/METADATA
gptchem-0.0.5.dist-info/WHEEL
gptchem-0.0.5.dist-info/top_level.txt
gptchem-0.0.5.dist-info/RECORD
