Metadata-Version: 2.1
Name: gptchem
Version: 0.0.5
Summary: Use GPT-3 to solve chemistry problems
Home-page: https://github.com/kjappelbaum/gptchem
Download-URL: https://github.com/kjappelbaum/gptchem/releases
Author: Kevin M. Jablonka
Author-email: mail@kjablonka.com
Maintainer: Kevin M. Jablonka
Maintainer-email: mail@kjablonka.com
License: MIT
Project-URL: Bug Tracker, https://github.com/kjappelbaum/gptchem/issues
Project-URL: Source Code, https://github.com/kjappelbaum/gptchem
Classifier: Development Status :: 1 - Planning
Classifier: Environment :: Console
Classifier: Intended Audience :: Developers
Classifier: License :: OSI Approved :: MIT License
Classifier: Operating System :: OS Independent
Classifier: Framework :: Pytest
Classifier: Framework :: tox
Classifier: Framework :: Sphinx
Classifier: Programming Language :: Python
Classifier: Programming Language :: Python :: 3.8
Classifier: Programming Language :: Python :: 3.9
Classifier: Programming Language :: Python :: 3.10
Classifier: Programming Language :: Python :: 3.11
Classifier: Programming Language :: Python :: 3 :: Only
Requires-Python: >=3.8
License-File: LICENSE
Requires-Dist: loguru
Requires-Dist: openai
Requires-Dist: fire
Requires-Dist: fastcore
Requires-Dist: typing-extensions
Requires-Dist: scikit-learn
Requires-Dist: pystow
Requires-Dist: pandas
Requires-Dist: selfies
Requires-Dist: rdkit
Requires-Dist: tenacity
Provides-Extra: docs
Requires-Dist: sphinx ; extra == 'docs'
Requires-Dist: furo ; extra == 'docs'
Requires-Dist: sphinx-autodoc-typehints ; extra == 'docs'
Requires-Dist: sphinx-automodapi ; extra == 'docs'
Requires-Dist: sphinx-copybutton ; extra == 'docs'
Provides-Extra: eval
Requires-Dist: fcd ; extra == 'eval'
Requires-Dist: pubchempy ; extra == 'eval'
Requires-Dist: pycm ; extra == 'eval'
Requires-Dist: submitit ; extra == 'eval'
Requires-Dist: guacamol ; extra == 'eval'
Requires-Dist: strsimpy ; extra == 'eval'
Requires-Dist: diskcache ; extra == 'eval'
Provides-Extra: experiments
Requires-Dist: colorcet ; extra == 'experiments'
Requires-Dist: SciencePlots ; extra == 'experiments'
Requires-Dist: pycm ; extra == 'experiments'
Requires-Dist: xgboost ; extra == 'experiments'
Provides-Extra: reprs
Requires-Dist: deepsmiles ; extra == 'reprs'
Provides-Extra: tests
Requires-Dist: pytest ; extra == 'tests'
Requires-Dist: coverage ; extra == 'tests'
